SharedMailbox/__init__.py
robotframework_sharedmailbox-1.0.0.dist-info/METADATA
robotframework_sharedmailbox-1.0.0.dist-info/WHEEL
robotframework_sharedmailbox-1.0.0.dist-info/top_level.txt
robotframework_sharedmailbox-1.0.0.dist-info/RECORD
