Metadata-Version: 2.1
Name: robotframework-sharedmailbox
Version: 1.0.0
Summary: Read shared mailboxes in Exchange 365 using Robot Framework.
Home-page: https://github.com/arvindmehairjan/robotframework-sharedmailbox
Author: Arvind Mehairjan
Author-email: 
License: MIT
Platform: UNKNOWN
Classifier: License :: OSI Approved :: MIT License
Classifier: Programming Language :: Python :: 3
Classifier: Programming Language :: Python :: 3.6
Classifier: Programming Language :: Python :: 3.7
Classifier: Programming Language :: Python :: 3.8
Classifier: Programming Language :: Python :: 3.9
Requires-Dist: exchangelib
